facto/__init__.py
facto/cli.py
facto/client.py
facto/crypto.py
facto/models.py
facto_ai-0.1.1.dist-info/METADATA
facto_ai-0.1.1.dist-info/WHEEL
facto_ai-0.1.1.dist-info/entry_points.txt
facto_ai-0.1.1.dist-info/top_level.txt
facto_ai-0.1.1.dist-info/RECORD
